EACheadtracker/HeadTracker.py
EACheadtracker/__init__.py
EACheadtracker/face_geometry.py
build/lib/build/lib/src/HeadTracker.py
build/lib/build/lib/src/__init__.py
build/lib/build/lib/src/face_geometry.py
build/lib/src/HeadTracker.py
build/lib/src/__init__.py
build/lib/src/face_geometry.py
src/HeadTracker.py
src/__init__.py
src/face_geometry.py
EACheadtracker-0.0.1.dist-info/METADATA
EACheadtracker-0.0.1.dist-info/WHEEL
EACheadtracker-0.0.1.dist-info/top_level.txt
EACheadtracker-0.0.1.dist-info/RECORD
