Metadata-Version: 2.1
Name: EACheadtracker
Version: 0.0.1
Summary: webcam headtracker
Home-page: https://github.com/eac-ufsm/webcam-headtracker
Author: Davi Carvalho
Author-email: r.davicarvalho@gmail.com
License: UNKNOWN
Project-URL: Bug Tracker, https://github.com/eac-ufsm/webcam-headtracker/issues
Platform: UNKNOWN
Classifier: Programming Language :: Python :: 3
Classifier: License :: OSI Approved :: MIT License
Classifier: Operating System :: OS Independent
Requires-Python: >=3.7
Requires-Dist: numpy
Requires-Dist: mediapipe
Requires-Dist: click
Requires-Dist: opencv-python
